robinwu/__init__.py
robinwu/myfunctions.py
robinwu-0.1.0.dist-info/METADATA
robinwu-0.1.0.dist-info/WHEEL
robinwu-0.1.0.dist-info/top_level.txt
robinwu-0.1.0.dist-info/RECORD
