Metadata-Version: 2.1
Name: robinwu
Version: 0.1.0
Summary: Robin Wu's first Python library
Home-page: UNKNOWN
Author: Me
Author-email: UNKNOWN
License: MIT
Platform: UNKNOWN
